date_format_machine/__init__.py
date_format_machine/dfm.py
date_format_machine/dfm_formats.yaml
date_format_machine-0.9.dist-info/entry_points.txt
date_format_machine-0.9.dist-info/WHEEL
date_format_machine-0.9.dist-info/METADATA
date_format_machine-0.9.dist-info/RECORD
