Metadata-Version: 2.1
Name: date-format-machine
Version: 0.9
Summary: Tool for manipulating date strings
Author: Ryan
Author-email: citizen.townshend@gmail.com
Requires-Python: >=3.10,<4.0
Classifier: Programming Language :: Python :: 3
Classifier: Programming Language :: Python :: 3.10
Requires-Dist: PyYAML (>=6.0,<7.0)
Requires-Dist: click (>=8.1.3,<9.0.0)
Requires-Dist: click-log (>=0.4.0,<0.5.0)
Requires-Dist: pendulum (>=2.1.2,<3.0.0)
Requires-Dist: tabulate (>=0.8.10,<0.9.0)
